pnap_ip_api/__init__.py
pnap_ip_api/api_client.py
pnap_ip_api/api_response.py
pnap_ip_api/configuration.py
pnap_ip_api/exceptions.py
pnap_ip_api/py.typed
pnap_ip_api/rest.py
pnap_ip_api/version.py
pnap_ip_api/api/__init__.py
pnap_ip_api/api/ip_blocks_api.py
pnap_ip_api/models/__init__.py
pnap_ip_api/models/delete_ip_block_result.py
pnap_ip_api/models/error.py
pnap_ip_api/models/ip_block.py
pnap_ip_api/models/ip_block_create.py
pnap_ip_api/models/ip_block_patch.py
pnap_ip_api/models/tag_assignment.py
pnap_ip_api/models/tag_assignment_request.py
pnap_ip_api-2.1.1.dist-info/METADATA
pnap_ip_api-2.1.1.dist-info/WHEEL
pnap_ip_api-2.1.1.dist-info/top_level.txt
pnap_ip_api-2.1.1.dist-info/RECORD
